tinyprogress/__init__.py
tinyprogress/tinyprogress.py
tinyprogress-1.2.0.dist-info/LICENSE
tinyprogress-1.2.0.dist-info/METADATA
tinyprogress-1.2.0.dist-info/WHEEL
tinyprogress-1.2.0.dist-info/top_level.txt
tinyprogress-1.2.0.dist-info/RECORD
