Metadata-Version: 2.1
Name: tinyprogress
Version: 1.2.0
Summary: A lightweight progress bar for Python without dependencies.
Home-page: https://github.com/croketillo/tinyprogress
Author: Croketillo
Author-email: croketillo@gmail.com
Classifier: Programming Language :: Python :: 3.8
Classifier: License :: OSI Approved :: GNU General Public License v3 or later (GPLv3+)
Classifier: Operating System :: OS Independent
Classifier: Intended Audience :: Developers
Classifier: Topic :: Software Development :: Libraries :: Python Modules
Classifier: Topic :: Utilities
Requires-Python: >=3.6
License-File: LICENSE
